{"content":[{"id":"testimonials-testimonials","heading":{"short":"What Our Clients Say","medium":"Hear from those who have worked with Hussain."},"sentence":{"short":"Clients love working with Hussain!","medium":"Hussain delivers exceptional results that exceed expectations.","long":"The feedback from clients highlights Hussain's creativity and professionalism in every project."},"overline":{"short":"Client Testimonials"},"button":{"short":"See More Reviews"},"testimonials":[{"testimonial":"Incredible work on my website! Very responsive.","customer-name":"Sarah T.","overline":"Web Development","customer-occupation":"Entrepreneur","customer-location":"New York, USA"},{"testimonial":"Hussain's designs are top-notch and very innovative.","customer-name":"Michael R.","overline":"Graphic Design","customer-occupation":"Marketing Manager","customer-location":"Los Angeles, USA"},{"testimonial":"The content writing was engaging and well-researched.","customer-name":"Emily K.","overline":"Content Writing","customer-occupation":"Blog Owner","customer-location":"Chicago, USA"}]}]}